pp_highlighting/__init__.py
pp_highlighting/pp_highlighter.py
pp_highlighting/pp_validator.py
pyparsing_highlighting-0.2.8.dist-info/LICENSE
pyparsing_highlighting-0.2.8.dist-info/METADATA
pyparsing_highlighting-0.2.8.dist-info/WHEEL
pyparsing_highlighting-0.2.8.dist-info/top_level.txt
pyparsing_highlighting-0.2.8.dist-info/RECORD
