Metadata-Version: 2.1
Name: pyparsing-highlighting
Version: 0.2.8
Summary: Syntax highlighting for prompt_toolkit and HTML with pyparsing.
Home-page: https://github.com/crowsonkb/pyparsing-highlighting
Author: Katherine Crowson
Author-email: crowsonkb@gmail.com
License: MIT
Keywords: console,highlighting,html,prompt,syntax,terminal
Platform: UNKNOWN
Classifier: Development Status :: 3 - Alpha
Classifier: Environment :: Console
Classifier: Environment :: Web Environment
Classifier: Intended Audience :: Developers
Classifier: License :: OSI Approved :: MIT License
Classifier: Operating System :: OS Independent
Classifier: Programming Language :: Python :: 3.5
Classifier: Programming Language :: Python :: 3.6
Classifier: Programming Language :: Python :: 3.7
Classifier: Programming Language :: Python :: 3.8
Classifier: Topic :: Internet :: WWW/HTTP
Classifier: Topic :: Software Development :: Libraries :: Python Modules
Classifier: Topic :: Software Development :: User Interfaces
Classifier: Topic :: Terminals
Requires-Python: >=3.5
Requires-Dist: prompt-toolkit (>=2.0.0)
Requires-Dist: pyparsing (>=2.2.0)
